{"other_decide": ["  decide the destination","finalie the destination","shortlist the destination"], "other_find_cost": ["  find cost of tickets","look up the cost of tickets","check ticket costs"], "check_time_table": [" check time-table","comfirm timings from thetime table","find the timings of the bus"], "find_bus": [" find the bus to your destination","find a suitable bus","finalize an appropriate bus"], "get_bus_stop": [" get to the bus stop","reach the bus stop","arrive at the bus stop"], "wait": [" wait for the bus to arrive","wait for arrival of bus","wait till the bus arrives"], "other_signal_driver": ["  signal driver","signal the driver to halt","wave to stop"], "bus_comes": [" bus comes to the stop ","bus halts at the bus stop","bus reaches the bus stop"], "other_driver_opens_door": ["  driver opens door","the door is opened by the driver","the door opens"], "board_bus": [" board the bus","get on the bus","enter the bus"], "RelNScrEv": [" RelNScrEv"], "get_ticket": [" get ticket","purchase the ticket","buy the ticket"], "find_place":[" find a place","locate a place","navigate to a nice place"], "ride": ["ride the bus","ride to the destination","ride the bus till the destination"], "press_stop_button": [" press stop button at the destination","push the stop button"," stop the bus by pressing the stop button"], "spend_time_bus": ["spend time on the bus","pass time","wait till destination is reached"], "go_exit": ["go exit the bus","vacate the bus","exit the bus"], "other_reach": [" reach the destination","arrive at the destination","get to the destination"], "bus_stops": [" bus stops","bus omes to a halt","the bus stops moving"], "other_thank": ["  thank the driver","remmeber to thank the driver","express gratitude to the driver"], "get_off": [" get off the bus","leave the bus","exit the bus"], "UnRelEv": " UnRelEvidently, this is not the case"}